rasa_core_sdk/__init__.py
rasa_core_sdk/constants.py
rasa_core_sdk/endpoint.py
rasa_core_sdk/events.py
rasa_core_sdk/executor.py
rasa_core_sdk/forms.py
rasa_core_sdk/utils.py
rasa_core_sdk/version.py
rasa_core_sdk/cli/__init__.py
rasa_core_sdk/cli/arguments.py
rasa_core_sdk-0.14.0.dist-info/LICENSE.txt
rasa_core_sdk-0.14.0.dist-info/METADATA
rasa_core_sdk-0.14.0.dist-info/WHEEL
rasa_core_sdk-0.14.0.dist-info/top_level.txt
rasa_core_sdk-0.14.0.dist-info/RECORD
